{
  "date": "2025-03-26",
  "update_count": 3,
  "stocks": {
    "600468": {
      "name": "百利电气",
      "code": "600468",
      "board": "SH",
      "industry": "电力设备-电网设备-输变电设备",
      "concepts": [
        "柔性直流输电",
        "可控核聚变",
        "智能电网",
        "核电",
        "风电",
        "海工装备",
        "超导概念",
        "军工",
        "军民融合",
        "储能",
        "氢能源",
        "一带一路",
        "京津冀一体化",
        "国企改革",
        "沪股通"
      ],
      "mention_count": 1,
      "products": [],
      "core_business": [
        "超导材料核心供应商"
      ],
      "industry_position": [],
      "chain": [],
      "partners": [
        "超导材料核心供应商"
      ],
      "articles": [
        {
          "title": "20250326-今日操作建议参考",
          "date": "2025-03-26",
          "source": "https://mp.weixin.qq.com/s/PEo6dkchTcbFMcSWWhhKBQ",
          "accidents": [],
          "insights": [
            "超导材料核心供应商"
          ],
          "key_metrics": [],
          "target_valuation": [
            "超导材料核心供应商"
          ],
          "content": "",
          "analysis": "",
          "summary": ""
        }
      ],
      "article_count": 1,
      "valuation": {
        "target_market_cap": null,
        "pe_ratio": null,
        "pb_ratio": null
      },
      "financial_metrics": {
        "revenue_growth": null,
        "profit_margin": null,
        "roe": null
      },
      "market_data": {
        "market_cap": null,
        "circulating_market_cap": null,
        "total_shares": null,
        "circulating_shares": null
      }
    },
    "301082": {
      "name": "久盛电气",
      "code": "301082",
      "board": "SZ",
      "industry": "电力设备-电网设备-线缆部件及其他",
      "concepts": [
        "可控核聚变",
        "核电",
        "光热发电",
        "高压快充",
        "储能",
        "专精特新",
        "页岩气",
        "融资融券"
      ],
      "products": [],
      "core_business": [],
      "industry_position": [],
      "chain": [],
      "partners": [],
      "article_count": 1,
      "articles": [
        {
          "title": "2025年3月26日市场复盘及下步操作建议",
          "date": "2025-03-26",
          "source": "https://mp.weixin.qq.com/s/Z5rTx3sN-hl21DMVbrPm_w",
          "accidents": [],
          "insights": [],
          "key_metrics": [
            "细分领域：真空磁流体密封系统市占率90%，解决核聚变装置氚泄漏核心痛点"
          ],
          "target_valuation": [],
          "content": "",
          "analysis": "",
          "summary": ""
        }
      ],
      "valuation": {
        "target_market_cap": null,
        "pe_ratio": null,
        "pb_ratio": null
      },
      "financial_metrics": {
        "revenue_growth": null,
        "profit_margin": null,
        "roe": null
      },
      "market_data": {
        "market_cap": null,
        "circulating_market_cap": null,
        "total_shares": null,
        "circulating_shares": null
      }
    },
    "002923": {
      "name": "润都股份",
      "code": "002923",
      "board": "SZ",
      "industry": "医药生物-化学制药-化学制剂",
      "concepts": [
        "仿制药一致性评价",
        "青蒿素",
        "合成生物",
        "创新药",
        "医疗器械概念",
        "医药电商",
        "肝炎概念",
        "流感",
        "猴痘概念",
        "幽门螺杆菌概念"
      ],
      "products": [],
      "core_business": [],
      "industry_position": [],
      "chain": [],
      "partners": [],
      "article_count": 1,
      "articles": [
        {
          "title": "2025年3月26日市场复盘及下步操作建议",
          "date": "2025-03-26",
          "source": "https://mp.weixin.qq.com/s/Z5rTx3sN-hl21DMVbrPm_w",
          "accidents": [],
          "insights": [],
          "key_metrics": [
            "技术储备：拥有医用级尼古丁萃取专利，年产能500吨（全球第三）"
          ],
          "target_valuation": [],
          "content": "",
          "analysis": "",
          "summary": ""
        }
      ],
      "valuation": {
        "target_market_cap": null,
        "pe_ratio": null,
        "pb_ratio": null
      },
      "financial_metrics": {
        "revenue_growth": null,
        "profit_margin": null,
        "roe": null
      },
      "market_data": {
        "market_cap": null,
        "circulating_market_cap": null,
        "total_shares": null,
        "circulating_shares": null
      }
    }
  }
}